odoo8_addon_openeducat_erp-8.0.1.2.0-py2.7-nspkg.pth
odoo_addons/openeducat_erp/__openerp__.py
odoo_addons/openeducat_erp/utils.py
odoo_addons/openeducat_erp/__init__.py
odoo_addons/openeducat_erp/op_subject/op_subject_view.xml
odoo_addons/openeducat_erp/op_subject/__init__.py
odoo_addons/openeducat_erp/op_subject/op_subject.py
odoo_addons/openeducat_erp/op_exam_room/__init__.py
odoo_addons/openeducat_erp/op_exam_room/op_exam_room.py
odoo_addons/openeducat_erp/op_exam_room/op_exam_room_view.xml
odoo_addons/openeducat_erp/res_company/__init__.py
odoo_addons/openeducat_erp/res_company/res_company.py
odoo_addons/openeducat_erp/res_company/res_company.xml
odoo_addons/openeducat_erp/op_tag/__init__.py
odoo_addons/openeducat_erp/op_tag/op_tag.py
odoo_addons/openeducat_erp/op_tag/op_tag_view.xml
odoo_addons/openeducat_erp/op_timetable/op_timetable.py
odoo_addons/openeducat_erp/op_timetable/op_timetable_view.xml
odoo_addons/openeducat_erp/op_timetable/__init__.py
odoo_addons/openeducat_erp/security/op_security.xml
odoo_addons/openeducat_erp/security/ir.model.access.csv
odoo_addons/openeducat_erp/op_result_line/op_result_line.py
odoo_addons/openeducat_erp/op_result_line/__init__.py
odoo_addons/openeducat_erp/op_result_line/op_result_line_view.xml
odoo_addons/openeducat_erp/op_vehicle/op_vehicle.py
odoo_addons/openeducat_erp/op_vehicle/__init__.py
odoo_addons/openeducat_erp/op_vehicle/op_vehicle_view.xml
odoo_addons/openeducat_erp/op_scholarship_type/op_scholarship_type_view.xml
odoo_addons/openeducat_erp/op_scholarship_type/__init__.py
odoo_addons/openeducat_erp/op_scholarship_type/op_scholarship_type.py
odoo_addons/openeducat_erp/op_book_purchase/op_book_purchase.py
odoo_addons/openeducat_erp/op_book_purchase/op_book_purchase_view.xml
odoo_addons/openeducat_erp/op_book_purchase/__init__.py
odoo_addons/openeducat_erp/op_attendance_sheet/op_attendance_sheet_view.xml
odoo_addons/openeducat_erp/op_attendance_sheet/__init__.py
odoo8_addon_openeducat_erp-8.0.1.2.0.dist-info/top_level.txt
odoo8_addon_openeducat_erp-8.0.1.2.0.dist-info/WHEEL
odoo8_addon_openeducat_erp-8.0.1.2.0.dist-info/RECORD
odoo8_addon_openeducat_erp-8.0.1.2.0.dist-info/metadata.json
odoo8_addon_openeducat_erp-8.0.1.2.0.dist-info/DESCRIPTION.rst
odoo8_addon_openeducat_erp-8.0.1.2.0.dist-info/METADATA
odoo8_addon_openeducat_erp-8.0.1.2.0.dist-info/namespace_packages.txt
