Metadata-Version: 2.0
Name: odoo8-addon-openeducat-erp
Version: 8.0.1.2.0
Summary: Manage Students, Faculties and Education Institute
Home-page: http://www.openeducat.org
Author: UNKNOWN
Author-email: UNKNOWN
License: UNKNOWN
Platform: UNKNOWN
Requires-Dist: odoo (<9.0a,>=8.0a)
Classifier: Programming Language :: Python :: 2.7
Classifier: Framework :: Odoo
